metronotation/__init__.py
metronotation/__main__.py
metronotation/canvas.py
metronotation/renderer.py
metronotation/routemap.py
metro_notation-0.8.0.dist-info/LICENSE
metro_notation-0.8.0.dist-info/METADATA
metro_notation-0.8.0.dist-info/WHEEL
metro_notation-0.8.0.dist-info/entry_points.txt
metro_notation-0.8.0.dist-info/top_level.txt
metro_notation-0.8.0.dist-info/RECORD
