Metadata-Version: 2.1
Name: metro-notation
Version: 0.8.0
Summary: Rubik's cube algorithm visualizer
Home-page: https://github.com/kitao/metro-notation
Author: Takashi Kitao
Author-email: takashi.kitao@gmail.com
License: MIT
Platform: UNKNOWN
Classifier: Development Status :: 4 - Beta
Classifier: Programming Language :: Python :: 3
Classifier: License :: OSI Approved :: MIT License
Classifier: Operating System :: MacOS
Classifier: Operating System :: Microsoft :: Windows
Classifier: Operating System :: POSIX :: Linux
Classifier: Topic :: Multimedia :: Graphics
Requires-Dist: pillow
